WorksConsultingPythonPackage/__init__.py
WorksConsultingPythonPackage/checks.py
WorksConsultingPythonPackage/editor.py
WorksConsultingPythonPackage/multiprocessing.py
WorksConsultingPythonPackage/time.py
WorksConsultingPythonPackage-0.1.2.dist-info/METADATA
WorksConsultingPythonPackage-0.1.2.dist-info/WHEEL
WorksConsultingPythonPackage-0.1.2.dist-info/top_level.txt
WorksConsultingPythonPackage-0.1.2.dist-info/RECORD
